stats_scraper/__init__.py
stats_scraper/__main__.py
stats_scraper/player.py
stats_scraper/scraper.py
stats_scraper-1.0.0.dist-info/METADATA
stats_scraper-1.0.0.dist-info/WHEEL
stats_scraper-1.0.0.dist-info/top_level.txt
stats_scraper-1.0.0.dist-info/RECORD
