Metadata-Version: 2.1
Name: stats-scraper
Version: 1.0.0
Summary: Scrapes NBA player data from basketball-reference.com and has few methods to sort the data
Home-page: https://github.com/JosephJ12/stats_scraper2
Author: Joseph Jung
Author-email: josephjung12@gmail.com
License: MIT
Platform: UNKNOWN
Classifier: License :: OSI Approved :: MIT License
Classifier: Programming Language :: Python :: 3
Classifier: Programming Language :: Python :: 3.7
Requires-Dist: requests
Requires-Dist: contextlib2
Requires-Dist: bs4
